{"answers":[{"acceptanceTime":"2022-04-26T04:21:23Z","answerContent":{"crowd-image-classifier":{"label":"Spotted"}},"submissionTime":"2022-04-26T04:21:37Z","timeSpentInSeconds":14.0,"workerId":"public.us-east-1.A234WZ4KX8IW07"},{"acceptanceTime":"2022-04-26T04:22:30Z","answerContent":{"crowd-image-classifier":{"label":"Spotted"}},"submissionTime":"2022-04-26T04:22:57Z","timeSpentInSeconds":27.0,"workerId":"public.us-east-1.A2J8AZUA3PHGNK"},{"acceptanceTime":"2022-04-26T04:22:44Z","answerContent":{"crowd-image-classifier":{"label":"Solid"}},"submissionTime":"2022-04-26T04:23:29Z","timeSpentInSeconds":45.0,"workerId":"public.us-east-1.AQIP3DSYXEXX5"},{"acceptanceTime":"2022-04-26T04:22:43Z","answerContent":{"crowd-image-classifier":{"label":"Striped"}},"submissionTime":"2022-04-26T04:24:10Z","timeSpentInSeconds":87.0,"workerId":"public.us-east-1.A1HU1TJZZ2SS1X"},{"acceptanceTime":"2022-04-26T04:25:44Z","answerContent":{"crowd-image-classifier":{"label":"Striped"}},"submissionTime":"2022-04-26T04:26:01Z","timeSpentInSeconds":17.0,"workerId":"public.us-east-1.AP1KNSGHIHPCO"}]}