[
    {
        "datasetObjectId": "0",
        "dataObject": {
            "s3Uri": "s3://birds-final-project-bucket/American_Goldfinch_0022_32111.jpg"
        },
        "annotations": [
            {
                "workerId": "public.us-east-1.A1D0WZIOU8ONY5",
                "annotationData": {
                    "content": "{\"crowd-image-classifier\":{\"label\":\"Multi-colored\"}}"
                }
            },
            {
                "workerId": "public.us-east-1.A2TO6N1MTMQD1B",
                "annotationData": {
                    "content": "{\"crowd-image-classifier\":{\"label\":\"Spotted\"}}"
                }
            },
            {
                "workerId": "public.us-east-1.A7SS3XTYL2W5D",
                "annotationData": {
                    "content": "{\"crowd-image-classifier\":{\"label\":\"Multi-colored\"}}"
                }
            }
        ]
    },
    {
        "datasetObjectId": "14",
        "dataObject": {
            "s3Uri": "s3://birds-final-project-bucket/White_Necked_Raven_0055_797352.jpg"
        },
        "annotations": [
            {
                "workerId": "public.us-east-1.A7SS3XTYL2W5D",
                "annotationData": {
                    "content": "{\"crowd-image-classifier\":{\"label\":\"Solid\"}}"
                }
            },
            {
                "workerId": "public.us-east-1.ACPF0GZBM5U2J",
                "annotationData": {
                    "content": "{\"crowd-image-classifier\":{\"label\":\"Solid\"}}"
                }
            },
            {
                "workerId": "public.us-east-1.A1Y5XHY97KETCJ",
                "annotationData": {
                    "content": "{\"crowd-image-classifier\":{\"label\":\"Solid\"}}"
                }
            }
        ]
    },
    {
        "datasetObjectId": "12",
        "dataObject": {
            "s3Uri": "s3://birds-final-project-bucket/Swainson_Warbler_0026_794884.jpg"
        },
        "annotations": [
            {
                "workerId": "public.us-east-1.ACPF0GZBM5U2J",
                "annotationData": {
                    "content": "{\"crowd-image-classifier\":{\"label\":\"Solid\"}}"
                }
            },
            {
                "workerId": "public.us-east-1.A2TO6N1MTMQD1B",
                "annotationData": {
                    "content": "{\"crowd-image-classifier\":{\"label\":\"Spotted\"}}"
                }
            },
            {
                "workerId": "public.us-east-1.A7SS3XTYL2W5D",
                "annotationData": {
                    "content": "{\"crowd-image-classifier\":{\"label\":\"Solid\"}}"
                }
            }
        ]
    },
    {
        "datasetObjectId": "3",
        "dataObject": {
            "s3Uri": "s3://birds-final-project-bucket/Cardinal_0092_17591.jpg"
        },
        "annotations": [
            {
                "workerId": "public.us-east-1.A3RR91G2KJO9NI",
                "annotationData": {
                    "content": "{\"crowd-image-classifier\":{\"label\":\"Solid\"}}"
                }
            },
            {
                "workerId": "public.us-east-1.A2TO6N1MTMQD1B",
                "annotationData": {
                    "content": "{\"crowd-image-classifier\":{\"label\":\"Spotted\"}}"
                }
            },
            {
                "workerId": "public.us-east-1.ACPF0GZBM5U2J",
                "annotationData": {
                    "content": "{\"crowd-image-classifier\":{\"label\":\"Spotted\"}}"
                }
            }
        ]
    },
    {
        "datasetObjectId": "7",
        "dataObject": {
            "s3Uri": "s3://birds-final-project-bucket/Least_Auklet_0014_1901.jpg"
        },
        "annotations": [
            {
                "workerId": "public.us-east-1.ARBNQGYZDEJUY",
                "annotationData": {
                    "content": "{\"crowd-image-classifier\":{\"label\":\"Spotted\"}}"
                }
            },
            {
                "workerId": "public.us-east-1.A2TO6N1MTMQD1B",
                "annotationData": {
                    "content": "{\"crowd-image-classifier\":{\"label\":\"Spotted\"}}"
                }
            },
            {
                "workerId": "public.us-east-1.ACPF0GZBM5U2J",
                "annotationData": {
                    "content": "{\"crowd-image-classifier\":{\"label\":\"Spotted\"}}"
                }
            }
        ]
    }
]