{"answers":[{"acceptanceTime":"2022-04-26T03:00:42Z","answerContent":{"crowd-image-classifier":{"label":"Multi-Colored"}},"submissionTime":"2022-04-26T03:00:52Z","timeSpentInSeconds":10.0,"workerId":"public.us-east-1.A2YO837C0O1E91"},{"acceptanceTime":"2022-04-26T03:03:07Z","answerContent":{"crowd-image-classifier":{"label":"Striped"}},"submissionTime":"2022-04-26T03:03:27Z","timeSpentInSeconds":20.0,"workerId":"public.us-east-1.AKFGCM6YXGVCA"},{"acceptanceTime":"2022-04-26T03:03:39Z","answerContent":{"crowd-image-classifier":{"label":"Spotted"}},"submissionTime":"2022-04-26T03:04:24Z","timeSpentInSeconds":45.0,"workerId":"public.us-east-1.A2H3RZ0D12FHVI"}]}